<?xml version="1.0"?>

<!DOCTYPE hibernate-mapping PUBLIC
        "-//Hibernate/Hibernate Mapping DTD 3.0//EN"
        "http://www.hibernate.org/dtd/hibernate-mapping-3.0.dtd">

<hibernate-mapping package="org.dddml.suidemocontracts.domain.order">
  
  <class name="AbstractOrderEvent" table="order_event" mutable="false" abstract="true">

	<composite-id name="orderEventId" class="org.dddml.suidemocontracts.domain.order.OrderEventId">
		<key-property name="id" ><column name="id" sql-type="VARCHAR(42)" /></key-property>
		<key-property name="version" ><column name="version" /></key-property>
	</composite-id>

    <discriminator column="event_type" type="string" />


    <property name="createdBy" column="created_by"/>

    <property name="createdAt" column="created_at" />

    <property name="commandId" column="command_id"/>
    <property name="commandType" column="command_type" length="50" />

    <subclass name="AbstractOrderEvent$OrderClobEvent" discriminator-value="OrderClobEvent">
      <property name="LobText" column="lob_text"/>
      <subclass name="AbstractOrderEvent$OrderCreated" discriminator-value="OrderCreated"/>
      <subclass name="AbstractOrderEvent$OrderItemRemoved" discriminator-value="OrderItemRemoved"/>
      <subclass name="AbstractOrderEvent$OrderItemQuantityUpdated" discriminator-value="OrderItemQuantityUpdated"/>
    </subclass>



  </class>
  
</hibernate-mapping>
